LICENSE
MANIFEST.in
README.rst
qhangups.desktop
qhangups.png
setup.py
QHangups.egg-info/PKG-INFO
QHangups.egg-info/SOURCES.txt
QHangups.egg-info/dependency_links.txt
QHangups.egg-info/entry_points.txt
QHangups.egg-info/requires.txt
QHangups.egg-info/top_level.txt
qhangups/__init__.py
qhangups/__main__.py
qhangups/browser.py
qhangups/conversations.py
qhangups/conversationslist.py
qhangups/conversationwidget.py
qhangups/qhangups.svg
qhangups/qhangups_disabled.svg
qhangups/qhangupsbrowser.ui
qhangups/qhangupsconversations.ui
qhangups/qhangupsconversationslist.ui
qhangups/qhangupsconversationwidget.ui
qhangups/qhangupssettings.ui
qhangups/settings.py
qhangups/ui_qhangupsbrowser.py
qhangups/ui_qhangupsconversations.py
qhangups/ui_qhangupsconversationslist.py
qhangups/ui_qhangupsconversationwidget.py
qhangups/ui_qhangupssettings.py
qhangups/utils.py
qhangups/version.py
qhangups/languages/qhangups_cs.qm
qhangups/languages/qhangups_cs.ts